[{"q": "Let x be (2*3)/(2 + 0). Suppose -d = -6*d - 4*m + 29, -5*d - x*m + 28 = 0. Suppose 0*s - d*s = -5. Is s at most 2/3?", "a": "False", "t": "bool"}, {"q": "Let b be 4 + (3 - 77345/330). Let q = 958369/2046 + b. Let i = q + -241. Are i and 1 unequal?", "a": "True", "t": "bool"}, {"q": "Suppose u - 7 = -w - w, -w + 17 = 5*u. Suppose 0 = -3*b - 2*b. Which is smaller: b or w?", "a": "b", "t": "string"}, {"q": "Suppose 2*o = 14 - 6, 5*d = -2*o + 293. Is d at least as big as 56?", "a": "True", "t": "bool"}, {"q": "Let q(c) = -3*c - 14. Let m be q(-8). Let w be (-33)/m*(4/(-24) + 1). Is w smaller than -3?", "a": "False", "t": "bool"}, {"q": "Suppose 0 = 112*u - 105*u + 77. Do u and 14 have the same value?", "a": "False", "t": "bool"}, {"q": "Let k(f) = -f**3 - 5*f**2 - 4*f + 3. Let g be k(-4). Let u be 6/(-152) - (-3 + g). Suppose 0 = 71*a - 23*a - 48. Is u bigger than a?", "a": "False", "t": "bool"}, {"q": "Let t = -169 - -167. Which is smaller: t or -23/8?", "a": "-23/8", "t": "float"}, {"q": "Suppose 7*q = -12*q + 2204. Suppose 2*k - p + 3*p = -144, 0 = 2*k - 3*p + 159. Let y = q + k. Which is greater: 40 or y?", "a": "y", "t": "string"}, {"q": "Suppose 3 = 3*t + 10*x - 5*x, 4 = 4*t + 2*x. Which is smaller: 2/105 or t?", "a": "2/105", "t": "float"}, {"q": "Three letters picked without replacement from {d: 1, h: 3, n: 3, x: 2, k: 6}. What is prob of picking 3 k?", "a": "4/91", "t": "float"}, {"q": "Two letters picked without replacement from {z: 8, v: 4, r: 1, n: 2, w: 2, o: 2}. What is prob of picking 1 v and 1 r?", "a": "4/171", "t": "float"}, {"q": "Two letters picked without replacement from blbllleelbll. What is prob of picking 1 b and 1 e?", "a": "1/11", "t": "float"}, {"q": "What is prob of picking 1 l and 1 r when two letters picked without replacement from {l: 2, r: 1, y: 2, i: 1, a: 1, o: 2}?", "a": "1/18", "t": "float"}, {"q": "Calculate prob of picking 1 b and 1 l when two letters picked without replacement from pbbbobaoplbb.", "a": "1/11", "t": "float"}, {"q": "Calculate prob of picking 1 k, 2 d and 1 p when four letters picked without replacement from {d: 3, p: 1, j: 5, k: 10, z: 1}.", "a": "2/323", "t": "float"}, {"q": "What is prob of picking 1 p and 1 w when two letters picked without replacement from {p: 1, s: 2, h: 2, w: 2, b: 1, n: 5}?", "a": "1/39", "t": "float"}, {"q": "Two letters picked without replacement from lflffllllfllfflllll. What is prob of picking 2 l?", "a": "26/57", "t": "float"}, {"q": "Two letters picked without replacement from qjjjjpqq. Give prob of picking 2 j.", "a": "3/14", "t": "float"}, {"q": "What is prob of picking 3 q and 1 f when four letters picked without replacement from ffffqqfqqffqqfqqfq?", "a": "21/85", "t": "float"}, {"q": "List the prime factors of 2607647.", "a": "7, 17, 1289", "t": "tuple"}, {"q": "List the prime factors of 14477998.", "a": "2, 7238999", "t": "tuple"}, {"q": "List the prime factors of 5040134657.", "a": "1669, 3019853", "t": "tuple"}, {"q": "What are the prime factors of 985?", "a": "5, 197", "t": "tuple"}, {"q": "List the prime factors of 313005.", "a": "3, 5, 7, 11, 271", "t": "tuple"}, {"q": "What are the prime factors of 1101660?", "a": "2, 3, 5, 7, 43, 61", "t": "tuple"}, {"q": "List the prime factors of 5498.", "a": "2, 2749", "t": "tuple"}, {"q": "What are the prime factors of 104038971?", "a": "3, 79, 438983", "t": "tuple"}, {"q": "List the prime factors of 337861.", "a": "337861", "t": "int"}, {"q": "What are the prime factors of 1563339698?", "a": "2, 557, 1403357", "t": "tuple"}, {"q": "How many minutes are there between 10:52 PM and 9:22 AM?", "a": "630", "t": "int"}, {"q": "What is 457 minutes after 5:10 AM?", "a": "12:47 PM", "t": "string"}, {"q": "How many minutes are there between 9:43 AM and 11:33 AM?", "a": "110", "t": "int"}, {"q": "How many minutes are there between 9:10 PM and 11:35 PM?", "a": "145", "t": "int"}, {"q": "What is 345 minutes before 1:45 AM?", "a": "8:00 PM", "t": "string"}, {"q": "What is 680 minutes before 6:08 AM?", "a": "6:48 PM", "t": "string"}, {"q": "How many minutes are there between 8:49 AM and 2:34 PM?", "a": "345", "t": "int"}, {"q": "What is 609 minutes before 1:14 PM?", "a": "3:05 AM", "t": "string"}, {"q": "How many minutes are there between 8:40 AM and 11:54 AM?", "a": "194", "t": "int"}, {"q": "What is 4 minutes before 8:36 PM?", "a": "8:32 PM", "t": "string"}, {"q": "Let y(f) = 23*f**2 - 28*f - 4. Let n(r) = 572*r**2 - 693*r - 99. Let h(s) = 4*n(s) - 99*y(s). Let l(o) = -22*o - 4. Calculate h(l(w)).", "a": "5324*w**2 + 1936*w + 176", "t": "string"}, {"q": "Let b(l) = 6*l. Let j(k) = 5 - 4*k. Give b(j(i)).", "a": "30 - 24*i", "t": "string"}, {"q": "Let q(m) = 4 - 6*m. Let n(i) = 3 - 5*i. Let j(x) = -4*n(x) + 3*q(x). Let w(g) = 33*g. Calculate w(j(l)).", "a": "66*l", "t": "string"}, {"q": "Let j = 1 - 2. Let t be j + (2 - 5/(-1)). Let l(q) = 4*q**2 + 6. Let o(n) = -3*n**2 - 5. Let u(y) = t*o(y) + 5*l(y). Let v(c) = 2*c**2. Give u(v(m)).", "a": "8*m**4", "t": "string"}, {"q": "Let c(q) = 6080*q + 6079*q - 12177*q. Let r(w) = -311*w. Give r(c(b)).", "a": "5598*b", "t": "string"}, {"q": "Let h(q) = 8*q**2. Let d(v) be the third derivative of 3*v**2 + 0*v + 0*v**3 + 0 + 1/24*v**4. Give d(h(x)).", "a": "8*x**2", "t": "string"}, {"q": "Let i(f) = -2*f. Let r(n) be the second derivative of -n**5/60 - 6*n**2 - n. Let y(v) be the first derivative of r(v). What is i(y(l))?", "a": "2*l**2", "t": "string"}, {"q": "Let s(u) = -5*u. Let n = -17 + 20. Suppose -n*o = -4*g - 20, 2*g + 0*g = -3*o + 8. Let v(q) = q**2 + o*q**2 - 2*q**2. Calculate v(s(i)).", "a": "75*i**2", "t": "string"}, {"q": "Let f(m) = -693*m. Let a(i) = i - 25. What is f(a(y))?", "a": "17325 - 693*y", "t": "string"}, {"q": "Let f(i) = 2*i. Suppose 3*m + 32 = 7*m. Let t(a) = -34 + 34 - m*a. Let n(y) = -y. Let c(v) = -3*n(v) + t(v). Determine c(f(u)).", "a": "-10*u", "t": "string"}, {"q": "What is the f'th term of -4617, -3188, -1757, -324, 1111, 2548, 3987?", "a": "f**2 + 1426*f - 6044", "t": "string"}, {"q": "What is the c'th term of -9575, -9575, -9583, -9605, -9647, -9715?", "a": "-c**3 + 2*c**2 + c - 9577", "t": "string"}, {"q": "What is the v'th term of -2641, -2644, -2647, -2650?", "a": "-3*v - 2638", "t": "string"}, {"q": "What is the w'th term of -548534, -548533, -548554, -548609, -548710?", "a": "-2*w**3 + w**2 + 12*w - 548545", "t": "string"}, {"q": "What is the l'th term of -2199097, -2199104, -2199111?", "a": "-7*l - 2199090", "t": "string"}, {"q": "What is the k'th term of 180, 350, 520, 690, 860, 1030?", "a": "170*k + 10", "t": "string"}, {"q": "What is the f'th term of 8793, 8620, 8431, 8232, 8029?", "a": "f**3 - 14*f**2 - 138*f + 8944", "t": "string"}, {"q": "What is the g'th term of 8, -41, -104, -175, -248?", "a": "g**3 - 13*g**2 - 17*g + 37", "t": "string"}, {"q": "What is the d'th term of -459, -1488, -4279, -9714, -18675, -32044, -50703?", "a": "-147*d**3 + d**2 - 3*d - 310", "t": "string"}, {"q": "What is the g'th term of -76, -87, -104, -127, -156, -191, -232?", "a": "-3*g**2 - 2*g - 71", "t": "string"}, {"q": "Let m = 98030/9 + -10892. Let s = 1.8 - 0.8. Let u be 0/((-4)/((-4)/2)). Which is the smallest value?  (a) u  (b) m  (c) s  (d) -1", "a": "d", "t": "string"}, {"q": "Let k be ((-2)/4)/(10/(-8)). Let r be 8 + ((-546)/10)/7. Which is the biggest value?  (a) k  (b) r  (c) 0", "a": "a", "t": "string"}, {"q": "Let z = 1 + -1. Let r = 1417 + -1415. Which is the second biggest value?  (a) r  (b) -3/4  (c) z", "a": "c", "t": "string"}, {"q": "Let g = 0.077 - -0.023. Let v = -0.05 + 4.05. Which is the third biggest value?  (a) v  (b) -0.5  (c) g", "a": "b", "t": "string"}, {"q": "Suppose 0 = -4*h + 8*h - 464. Let n = h + -111. Which is the biggest value?  (a) -3  (b) n  (c) 3/7", "a": "b", "t": "string"}, {"q": "Let y = -31 + 24. Which is the second biggest value?  (a) y  (b) 0.3  (c) -3/7", "a": "c", "t": "string"}, {"q": "Let w = 14 + -10. Let y = -8 + w. Let k = -2 + 1.5. Which is the smallest value?  (a) -1/3  (b) k  (c) y", "a": "c", "t": "string"}, {"q": "Let j = 57 + -739/13. Let u = 68.5 + -70.5. Which is the third biggest value?  (a) j  (b) -0.5  (c) u", "a": "c", "t": "string"}, {"q": "Suppose p + 1 = 0, 64 = 3*t + 3*p - 11. Suppose 4*i - 3*v + 3 = -t, -3*i = -3*v + 24. Which is the third biggest value?  (a) -3  (b) i  (c) -2/15  (d) 11", "a": "a", "t": "string"}, {"q": "Let l = -97/35 + 25/7. Suppose 0*s = 2*s - 6. Which is the biggest value?  (a) s  (b) l  (c) 1", "a": "a", "t": "string"}, {"q": "What is the derivative of 226*f**3 - 8*f**2 + 10431 wrt f?", "a": "678*f**2 - 16*f", "t": "string"}, {"q": "Find the third derivative of -294681*n**5 + 621*n**2 + 93*n - 1.", "a": "-17680860*n**2", "t": "string"}, {"q": "What is the third derivative of 31641630*t*x**6 - 2*t*x**5 + 91*t*x**2 + 46*t + 193*x**2 + 3*x wrt x?", "a": "3796995600*t*x**3 - 120*t*x**2", "t": "string"}, {"q": "What is the first derivative of -5*g**2 + 34*g - 226?", "a": "34 - 10*g", "t": "string"}, {"q": "What is the third derivative of -1124028*h**3 + h**2 + 1473*h + 288?", "a": "-6744168", "t": "int"}, {"q": "Find the third derivative of 319*t**3*x**3 + 9*t**3*x**2 + 14*t*x**2 wrt x.", "a": "1914*t**3", "t": "string"}, {"q": "Find the second derivative of -g**4 + 11711448*g**3 - 157569565*g.", "a": "-12*g**2 + 70268688*g", "t": "string"}, {"q": "What is the derivative of 1121*s**3 - 149*s - 346300?", "a": "3363*s**2 - 149", "t": "string"}, {"q": "What is the third derivative of 177736*i**4 + 442408*i**2?", "a": "4265664*i", "t": "string"}, {"q": "Differentiate f**2 + 5*f*l + 602*f - 159134*l with respect to f.", "a": "2*f + 5*l + 602", "t": "string"}, {"q": "Calculate the remainder when 21106 is divided by 91.", "a": "85", "t": "int"}, {"q": "Calculate the remainder when 9688235 is divided by 4843839.", "a": "557", "t": "int"}, {"q": "What is the remainder when 567 is divided by 121?", "a": "83", "t": "int"}, {"q": "Calculate the remainder when 58544 is divided by 17.", "a": "13", "t": "int"}, {"q": "Calculate the remainder when 6129629 is divided by 2569.", "a": "2564", "t": "int"}, {"q": "What is the remainder when 12398512 is divided by 145?", "a": "142", "t": "int"}, {"q": "Calculate the remainder when 69483482 is divided by 1739.", "a": "1737", "t": "int"}, {"q": "Calculate the remainder when 1061402 is divided by 132673.", "a": "18", "t": "int"}, {"q": "What is the remainder when 124 is divided by 46?", "a": "32", "t": "int"}, {"q": "What is the remainder when 586577 is divided by 65174?", "a": "11", "t": "int"}, {"q": "Solve 997*l = 5*j + 1000*l - 11, 1 = -5*j + 3*l for j.", "a": "1", "t": "int"}, {"q": "Solve 2*o + 13 = 3*v, 5*v - 18 = 3*o + 2*v for o.", "a": "-5", "t": "int"}, {"q": "Solve 0 = -5*x - 2*b + 27, -123*x + 122*x + 7 = 2*b for x.", "a": "5", "t": "int"}, {"q": "Solve -152*l + 30 = -4*p - 154*l, 2*l = -2 for p.", "a": "-7", "t": "int"}, {"q": "Solve -3*u + 77 - 73 = 4*r, -4*r + u + 4 = 0 for r.", "a": "1", "t": "int"}, {"q": "Solve 2*j = -t + 8767 - 8771, -34 = 2*j + 4*t for j.", "a": "3", "t": "int"}, {"q": "Solve 2*s + 5*f + 34 = 0, 0 = -662*s + 659*s + 4*f - 28 for s.", "a": "-12", "t": "int"}, {"q": "Solve 5*j + a - 1 = 0, 3 - 5 = -4*j - 2*a for j.", "a": "0", "t": "int"}, {"q": "Solve -7 = 2*w + 3*n, 0*w - 2 = -3*w - 2*n for w.", "a": "4", "t": "int"}, {"q": "Solve 109*q - 4*v = 110*q - 35, -22 = -2*q - 2*v for q.", "a": "3", "t": "int"}, {"q": "Let f = -154 + 2620/17. Let q = -28.1 + 28. Which is the nearest to q?  (a) f  (b) 5  (c) -7", "a": "a", "t": "string"}, {"q": "Let c = 17.6 - 0.6. Let j = c + -13. What is the closest to 0.2 in -2, j, -0.2?", "a": "-0.2", "t": "float"}, {"q": "Let h = 0.17925 + 3.82075. Which is the closest to -3?  (a) 1/5  (b) h  (c) 0.147  (d) -0.5", "a": "d", "t": "string"}, {"q": "Let i(x) = -3*x - 24. Suppose 2*r - 8 = -62. Let m = -36 - r. Let f be i(m). Which is the nearest to 0.1?  (a) 5  (b) 4  (c) f", "a": "c", "t": "string"}, {"q": "Let m = 98 - 98.041. Let q = m - -0.541. What is the nearest to -1 in -0.1, 0.2, q?", "a": "-0.1", "t": "float"}, {"q": "Suppose 0 = 3*v + v. Suppose v = -2*h - 2. Let p = 2072 - 2075. Which is the closest to 1?  (a) h  (b) 0.4  (c) p", "a": "b", "t": "string"}, {"q": "Let y = -649 - -1261/2. Let b = y + 18. What is the nearest to -0.3 in -1, b, 3?", "a": "b", "t": "string"}, {"q": "Let j = -11698 + 11702. Let c = 1 - 1. What is the nearest to c in -2, 2/3, j?", "a": "2/3", "t": "float"}, {"q": "Let m be (-128)/((-28)/(-49)*7/(-2)). Let u = 16 - 18. What is the nearest to -1/3 in -4, 1/5, m, u?", "a": "1/5", "t": "float"}, {"q": "Let o = 807.1 + -805.1. What is the closest to 2/3 in o, 181, -2, -1?", "a": "o", "t": "string"}, {"q": "Put together 1145.154 and 13.", "a": "1158.154", "t": "float"}, {"q": "Put together -0.1092135 and -515770.", "a": "-515770.1092135", "t": "float"}, {"q": "What is 1 take away 0.7965897?", "a": "0.2034103", "t": "float"}, {"q": "What is 0.5 + 2654197.914?", "a": "2654198.414", "t": "float"}, {"q": "Subtract -450775965912 from 0.5.", "a": "450775965912.5", "t": "float"}, {"q": "What is the difference between 3 and -11829269.888?", "a": "11829272.888", "t": "float"}, {"q": "Add 555309 and 14321.", "a": "569630", "t": "int"}, {"q": "-7570.3 + -200745044", "a": "-200752614.3", "t": "float"}, {"q": "What is the difference between -31 and 104?", "a": "135", "t": "int"}, {"q": "-7 + -45118480", "a": "-45118487", "t": "int"}, {"q": "Collect the terms in 7*j - 26*j + 6*j + 10*j.", "a": "-3*j", "t": "string"}, {"q": "Collect the terms in 6 + 7 + 11687*o**3 - 5867*o**3 - 5827*o**3.", "a": "13 - 7*o**3", "t": "string"}, {"q": "Collect the terms in 27861*x + 19887*x + 7719*x - 16550*x.", "a": "38917*x", "t": "string"}, {"q": "Collect the terms in -q**2 - 2033 - 2052 + 4085.", "a": "-q**2", "t": "string"}, {"q": "Collect the terms in 111*y**2 - 556 + 556.", "a": "111*y**2", "t": "string"}, {"q": "Collect the terms in 8*t**2 + 12*t**2 + 25*t**2 - 10*t**2.", "a": "35*t**2", "t": "string"}, {"q": "Collect the terms in 130*y - 64*y + 33742621465*y**2 - 66*y - 33742621466*y**2.", "a": "-y**2", "t": "string"}, {"q": "Collect the terms in -3183 + 6*y**3 - 4*y**3 - 3*y**3 + 3183.", "a": "-y**3", "t": "string"}, {"q": "Collect the terms in 3 - 7 + 4 - 38493*j + 19238*j + 19282*j.", "a": "27*j", "t": "string"}, {"q": "Collect the terms in -2304492220779 + 2304492220779 - 3*l.", "a": "-3*l", "t": "string"}, {"q": "Suppose -90*z + 2*m - 11 = -91*z, m - 19 = -2*z. Solve 4*p - 3*p + z = 3*v, -2*v + 2*p = -2 for v.", "a": "4", "t": "int"}, {"q": "Let t = -423 - -463. Suppose t + 0 = 2*h. Solve 21 = f - 4*n - 0*n, 0 = -5*n - h for f.", "a": "5", "t": "int"}, {"q": "Let q(c) = -c**2 + 8*c + 1. Let v be q(8). Let x(i) = i**2 + 3 - v + 2*i - 4*i. Let o be x(3). Solve -o*l = -2*a - 4*l, -3*l - 4 = -4*a for a.", "a": "-2", "t": "int"}, {"q": "Let s = 191 + -214. Let w = s + 28. Solve -h - 17 = -2*u + 4*h, 14 = w*u - 3*h for u.", "a": "1", "t": "int"}, {"q": "Let h = -39 + 42. Solve 4*f + 2 = -h*y, -9 + 3 = 3*f for y.", "a": "2", "t": "int"}, {"q": "Let u(l) = 2*l + 30. Let m be u(-13). Let c = 5 - 0. Solve 2*a + c + 4 = n, m*a + 19 = n for n.", "a": "-1", "t": "int"}, {"q": "Suppose -3*x = 5 - 11. Let t = x + 0. Let h = 4 + -2. Solve 5*j = -0*j + q + 5, h*q = -2*j + t for j.", "a": "1", "t": "int"}, {"q": "Let y = 886 - 882. Solve 0 = -5*o - y*n + n - 20, -5*o - n - 20 = 0 for o.", "a": "-4", "t": "int"}, {"q": "Suppose 5*h - 10 = 0, 0 = -17*y + 19*y + 5*h + 170. Let m = y + 94. Solve 0 = m*v - 2*w + 8, -5*v + 2*w = 12 - 0 for v.", "a": "-4", "t": "int"}, {"q": "Let n = 2986 - 2986. Solve 5*j - 4*f + 16 = n, -2*j + 3 = -5*f + 6 for j.", "a": "-4", "t": "int"}, {"q": "Let b(m) = m**2 - 6*m - 6. Let a be ((-24)/(-10))/(-12 + 744/60). Determine b(a).", "a": "-6", "t": "int"}, {"q": "Let r(b) = -b - 2. Let d be r(-1). Let s be 0/(-4) + (-1 - d). Let m(h) = -h**2 - h + 7. Give m(s).", "a": "7", "t": "int"}, {"q": "Let r(q) be the second derivative of -q**6/120 - q**5/15 - q**4/12 - q**3/6 - 5*q**2/2 - 5*q. Let y(v) be the first derivative of r(v). Determine y(-4).", "a": "7", "t": "int"}, {"q": "Let p(o) = o + 4. Let w(j) = 5*j**3 - j**2 - j + 1. Let b = -9 + 10. Let k be w(b). Suppose 0*s - 4*s = 2*a - 12, -k*s = -4*a - 36. Determine p(s).", "a": "9", "t": "int"}, {"q": "Let i(g) = -21*g - 11. Let m(t) = -33*t - 16. Let u(n) = -8*i(n) + 5*m(n). Calculate u(-9).", "a": "-19", "t": "int"}, {"q": "Let z = -9 + 11. Let h(f) be the first derivative of -1/2*f**2 - z + 9*f. Calculate h(5).", "a": "4", "t": "int"}, {"q": "Let p = -171 - -173. Let k(q) = 83*q**2 - 84*q**p + 0*q - 6*q - 2. Determine k(-3).", "a": "7", "t": "int"}, {"q": "Let b(f) = f**3 + 1716*f**2 - f - 1 - 1716*f**2. Let r(l) = 12*l**3 + l**2 - 2*l - 3. Let c(q) = -4*b(q) + r(q). Give c(-1).", "a": "-8", "t": "int"}, {"q": "Suppose -2 + 18 = 2*r. Suppose 2*s - 2 = 2*c + r, -5*c - 4*s + 2 = 0. Let h(q) = 2*q**2 + q - 3. Give h(c).", "a": "3", "t": "int"}, {"q": "Let k(g) = 39 - 2*g. Let p = 73 + -67. Let h(x) = 3*x + 1. Let y be h(p). Let t be k(y). Let i(o) = 5*o**3 + 2*o - 1. Determine i(t).", "a": "6", "t": "int"}, {"q": "Calculate the highest common factor of 25 and 425.", "a": "25", "t": "int"}, {"q": "What is the highest common divisor of 361 and 304?", "a": "19", "t": "int"}, {"q": "What is the highest common factor of 2900 and 33524?", "a": "116", "t": "int"}, {"q": "Calculate the greatest common divisor of 6142725 and 19665.", "a": "1035", "t": "int"}, {"q": "What is the highest common factor of 5 and 131135?", "a": "5", "t": "int"}, {"q": "Calculate the highest common divisor of 63420544 and 114576.", "a": "5456", "t": "int"}, {"q": "Calculate the highest common factor of 187 and 68.", "a": "17", "t": "int"}, {"q": "Calculate the highest common factor of 8657 and 5599.", "a": "11", "t": "int"}, {"q": "Calculate the highest common factor of 33760 and 10.", "a": "10", "t": "int"}, {"q": "What is the highest common divisor of 30 and 397155?", "a": "15", "t": "int"}, {"q": "Does 39 divide 84006?", "a": "True", "t": "bool"}, {"q": "Is 3065850 a multiple of 50?", "a": "True", "t": "bool"}, {"q": "Does 239 divide 15968?", "a": "False", "t": "bool"}, {"q": "Is 23 a factor of 173811?", "a": "True", "t": "bool"}, {"q": "Is 294323 a multiple of 6?", "a": "False", "t": "bool"}, {"q": "Is 1187 a factor of 112004555?", "a": "False", "t": "bool"}, {"q": "Is 14 a factor of 3603922?", "a": "True", "t": "bool"}, {"q": "Is 97 a factor of 21959998?", "a": "False", "t": "bool"}, {"q": "Is 21769 a multiple of 77?", "a": "False", "t": "bool"}, {"q": "Does 88 divide 509424?", "a": "False", "t": "bool"}, {"q": "Suppose 5 = 3*r + 23. Let y = r + 9. Let i = -2 + y. Solve i = j + 2 for j.", "a": "-1", "t": "int"}, {"q": "Suppose 3*x + 9 = 0, 4*x = -2*n + 5*n - 21. Solve n*r = 7*r + 16 for r.", "a": "-4", "t": "int"}, {"q": "Let j = 2293 + -2278. Solve 91*r + j = 86*r for r.", "a": "-3", "t": "int"}, {"q": "Let f be 54/12*24/54. Let b(w) = w**2 - 3*w - 8. Let d(z) = z**2 - z. Let l be d(-2). Let r be b(l). Solve -f = 4*o - r for o.", "a": "2", "t": "int"}, {"q": "Let o = 146 - 135. Let f be 0*(3 - o/((-132)/(-40))). Let d be (1 + 0)*(-1 - -1). Solve f = -d*y + 3*y + 12 for y.", "a": "-4", "t": "int"}, {"q": "Suppose -81*n - 56*n = 203*n + 19*n. Solve n = 23*z - 11*z - 72 for z.", "a": "6", "t": "int"}, {"q": "Let p = 13 + -7. Suppose -2*n = -4*f + 50, f - 5*n + 55 = p*f. Suppose -5*m + f = -j, 2*j - m - 15 = -4*m. Solve 0 - 15 = j*s for s.", "a": "-5", "t": "int"}, {"q": "Let l(c) be the second derivative of c**5/20 - 2*c**4/3 + c**3/6 - 2*c**2 + 9*c. Let s be l(8). Solve 0 = -0*k - k - s for k.", "a": "-4", "t": "int"}, {"q": "Let p = 6102 + -6099. Let y(b) = b**3 + 7*b**2 - 6*b + 16. Let l be y(-8). Solve 9 = p*x - l for x.", "a": "3", "t": "int"}, {"q": "Let t be 1 + 42/(-36) - (-661)/6. Let l = -90 + t. Suppose -c + 5*c = 28. Solve 0 = -c*o + 3*o - l for o.", "a": "-5", "t": "int"}, {"q": "Let d(t) = 2*t**2 - 30*t - 29. Let g be d(16). Put g, 0, 2 in descending order.", "a": "g, 2, 0", "t": "string"}, {"q": "Let w = 0.6194 - -3.4176. Let f = w + -0.037. Let y = -0.8 + 0.92. Put f, y, 1 in ascending order.", "a": "y, 1, f", "t": "string"}, {"q": "Let s = -6670 + 6667. Let r = 52 - 48. Put -1, -11, r, s in descending order.", "a": "r, -1, s, -11", "t": "string"}, {"q": "Let m(g) = -g**2 - 1. Let i be m(-2). Let b be (-6)/30*(i - 0). Suppose 5*x = 15, -5*r - x + 2*x = 18. Put r, 3, b in increasing order.", "a": "r, b, 3", "t": "string"}, {"q": "Let s(i) = -i - 13. Let m be s(-9). Let b = m + -1. Suppose 4*k - 2*d = 10, 3*k = 4*k + d - 1. Put k, 0, b in descending order.", "a": "k, 0, b", "t": "string"}, {"q": "Let m = -4 + 1. Let f = -38.68 + 34.68. Put f, m, 2/5 in descending order.", "a": "2/5, m, f", "t": "string"}, {"q": "Let b = -424 + 433. Let v(k) = 66 - 8*k. Let c be v(b). Sort c, 5, -0.3, -3 in descending order.", "a": "5, -0.3, -3, c", "t": "string"}, {"q": "Suppose 4*f - 37 = -5*i, -5*f - 6 - 4 = -5*i. Suppose -i*g + 4 = -11. Let b be 2/g - (-2)/(-9). Sort -1/9, b, 1/9.", "a": "-1/9, 1/9, b", "t": "string"}, {"q": "Suppose 2*a - 3*a = -2, 5*p - 2*a - 21 = 0. Suppose r + p = 3. Put 1, -4, r in ascending order.", "a": "-4, r, 1", "t": "string"}, {"q": "Let y(l) = 13*l. Let n be y(1). Let u = -21250 - -21248. Sort -4, n, u in ascending order.", "a": "-4, u, n", "t": "string"}, {"q": "Suppose -576 = -p - 2*c + 501, 5406 = 5*p + 3*c. List the prime factors of p.", "a": "3, 19", "t": "tuple"}, {"q": "Suppose 0 = t - 5 + 1. Suppose 0 = t*d + 7*w - 4*w - 154, 3*w - 6 = 0. What are the prime factors of d?", "a": "37", "t": "int"}, {"q": "Let m(u) = 19*u**2 + 399*u - 9. What are the prime factors of m(-23)?", "a": "5, 173", "t": "tuple"}, {"q": "Let s(i) = 24 - i. Let l = 31 + -23. Let v be (l/(-2))/(-2) + 5. What are the prime factors of s(v)?", "a": "17", "t": "int"}, {"q": "Let b(d) = 1 - 3 - 4*d**2 + 7*d - 2. Let s(u) = -8*u**2 + 15*u - 8. Let t(p) = -5*b(p) + 2*s(p). What are the prime factors of t(3)?", "a": "5", "t": "int"}, {"q": "Let x(c) = -c**2 + 9*c. Let b be 16*3*(-3)/(-18). List the prime factors of x(b).", "a": "2", "t": "int"}, {"q": "Suppose 3*s = 2*q + 8*s - 617, 0 = 5*q + 3*s - 1495. List the prime factors of q.", "a": "2, 37", "t": "tuple"}, {"q": "Let d(w) be the third derivative of -w**6/120 - w**5/12 + 3*w**4/8 + 7*w**3/6 - 3*w**2. Let h be d(-7). Suppose 0 = q + 2*q - h. List the prime factors of q.", "a": "2, 7", "t": "tuple"}, {"q": "Suppose 4*n + 225 = 3*x, 5*n + 279 = -x + 4*x. Let t = n - -166. Suppose -t = 2*y - 6*y. List the prime factors of y.", "a": "2, 7", "t": "tuple"}, {"q": "Suppose 5*m + 118*j = 114*j + 10093, 2*j = -6. What are the prime factors of m?", "a": "43, 47", "t": "tuple"}, {"q": "Expand (-3 - 3*n + 3)*(-2*n + 0*n + n)*(5 - 1 - 2 + (-2 + 2 + 4)*(-3 + 4 + 0) + 1 - 1 - 1).", "a": "15*n**2", "t": "string"}, {"q": "Expand (0 + 0 - 20*g)*(-2*g**3 + 0*g + 0*g).", "a": "40*g**4", "t": "string"}, {"q": "Expand i**3 + i**3 - 5*i**3 - 4*i**3 + 3*i**3 - i**3 + (-2*i**2 + i**2 + 0*i**2)*(3*i + 4*i - 5*i + (20 + 4 - 8)*(-6*i - 3*i + 5*i)).", "a": "57*i**3", "t": "string"}, {"q": "Expand (-3 + 2 + 7 + (5 - 4 - 2)*(-3 - 1 + 5) - 1 + 0 + 0)*(u**3 + u + u**3 - u**3).", "a": "4*u**3 + 4*u", "t": "string"}, {"q": "Expand (a**3 - 4*a**3 + 4*a**3)*(-4*a**2 - 2*a**2 + 9*a**2)*(-94 - 69 + 36).", "a": "-381*a**5", "t": "string"}, {"q": "Expand (d**4 + 0*d**4 + 0*d**4)*(-3 - 1 + 6) - d**4 + 5*d**4 + 2*d**4 + 2*d**4 - 1 + 2*d + 1.", "a": "10*d**4 + 2*d", "t": "string"}, {"q": "Expand (5 + 9*v - 5)*(-2 + 6 + 10 + 19).", "a": "297*v", "t": "string"}, {"q": "Expand -3*s**2 - 2*s**3 + 3*s**2 + (2*s - 4*s + 3*s)*(2*s - s - 2*s)*(-217*s + 181*s + 137*s).", "a": "-103*s**3", "t": "string"}, {"q": "Expand (-3*x + x + 3*x + 6*x + 4*x + 8*x + (3 - 3 + 1)*(6*x - 4*x - 5*x) + (-2*x + 2*x + 2*x)*(1 - 2 + 3) - 5*x - x + 4*x - 1 + x + 1)*(1 + 2 - 7) + x - x - x.", "a": "-77*x", "t": "string"}, {"q": "Expand (-514*h + 514*h - 7*h**4 + (3 - 3 - 1)*(-2*h**4 + 4*h**4 - 4*h**4))*(4 - 3 - 4).", "a": "15*h**4", "t": "string"}, {"q": "Put -19370, -3, 4, 8, 3 in descending order.", "a": "8, 4, 3, -3, -19370", "t": "tuple"}, {"q": "Put 4, -4, 1, 2 in decreasing order.", "a": "4, 2, 1, -4", "t": "tuple"}, {"q": "Sort 1/20, -2, -0.4, 1/9 in descending order.", "a": "1/9, 1/20, -0.4, -2", "t": "tuple"}, {"q": "Sort -3, 23, 17, 3, 4, -1 in ascending order.", "a": "-3, -1, 3, 4, 17, 23", "t": "tuple"}, {"q": "Sort -5, -4, 1/5, 1/7, 0.28.", "a": "-5, -4, 1/7, 1/5, 0.28", "t": "tuple"}, {"q": "Put 15243, 3, -5 in descending order.", "a": "15243, 3, -5", "t": "tuple"}, {"q": "Sort 2, -47, 0, -1 in increasing order.", "a": "-47, -1, 0, 2", "t": "tuple"}, {"q": "Sort -4, 3, -297, -1, -1135, -62 in increasing order.", "a": "-1135, -297, -62, -4, -1, 3", "t": "tuple"}, {"q": "Sort -2/15, 1471, 0.1 in decreasing order.", "a": "1471, 0.1, -2/15", "t": "tuple"}, {"q": "Put -5, -3, -16, 5, 8 in increasing order.", "a": "-16, -5, -3, 5, 8", "t": "tuple"}, {"q": "What is 16/6*6/28*(-567)/(-756)?", "a": "3/7", "t": "float"}, {"q": "Calculate 25/(-20)*4/50.", "a": "-1/10", "t": "float"}, {"q": "Calculate (-240)/(-3300)*10/4.", "a": "2/11", "t": "float"}, {"q": "Calculate (18/(-12))/(63/231)*(-4)/2.", "a": "11", "t": "int"}, {"q": "Evaluate 2/(-129)*(-51)/(238/(-14)).", "a": "-2/43", "t": "float"}, {"q": "Evaluate (((-459)/(-68))/9)/((-1)/(-4)).", "a": "3", "t": "int"}, {"q": "Calculate -1*((-28)/4452)/(1/(-6)).", "a": "-2/53", "t": "float"}, {"q": "((-7)/(-70)*5)/(2/(-4))", "a": "-1", "t": "int"}, {"q": "Evaluate ((0/(-6))/12)/(6/(-3)).", "a": "0", "t": "int"}, {"q": "What is the value of -3*(-4)/12*(-7)/63?", "a": "-1/9", "t": "float"}, {"q": "Suppose -k + 0*s - 4*s + 58 = 0, 0 = k - s - 33. Calculate the remainder when 65 is divided by k.", "a": "27", "t": "int"}, {"q": "Let d(i) = 2*i**3 + 19*i**2 + 2*i. Let x be d(-9). Let o = -40 + x. Suppose -3*c = -10 - o. What is the remainder when c is divided by 7?", "a": "4", "t": "int"}, {"q": "Suppose -2*i + 126 = i. Let b = -12 + 23. Calculate the remainder when i is divided by b.", "a": "9", "t": "int"}, {"q": "Let u(p) = 17*p**2 + p. Let r be u(2). Let s = r - 6. Suppose 5*g = g + s. What is the remainder when 30 is divided by g?", "a": "14", "t": "int"}, {"q": "Suppose 0 = -49*t + 7528 - 3167. Calculate the remainder when 264 is divided by t.", "a": "86", "t": "int"}, {"q": "Suppose 20 = 8*t - 6*t. What is the remainder when t is divided by 3?", "a": "1", "t": "int"}, {"q": "Calculate the remainder when 30 is divided by (-4)/14 + 464/56.", "a": "6", "t": "int"}, {"q": "Suppose k - 90 = -4*k. What is the remainder when k is divided by 5?", "a": "3", "t": "int"}, {"q": "Let c = 553 + -507. What is the remainder when 51 is divided by c?", "a": "5", "t": "int"}, {"q": "Let z = 4 - 6. Let a(y) = -24*y - 2. Let g = 2 - -14. What is the remainder when a(z) is divided by g?", "a": "14", "t": "int"}, {"q": "Let h be ((-320)/(-12) - -2)/(3/9). Calculate the greatest common factor of 129 and h.", "a": "43", "t": "int"}, {"q": "Let w(o) = 3*o**2 + 2*o. Suppose -a - 3*v = -4*a + 12, 10 = 4*a - 2*v. Let q be w(a). Let h = -4 - -9. Calculate the highest common divisor of q and h.", "a": "5", "t": "int"}, {"q": "Let i = 5 - 2. Let x(m) = 3*m**3 + m**2 - 3*m - 4. Let q be x(i). Let g = -49 - -60. What is the highest common factor of g and q?", "a": "11", "t": "int"}, {"q": "Let t(r) = -2 + 4*r + 1 - 2*r**3 + r**2 + 2 + 1. Let l be t(-2). Let f = -1 + 3. Calculate the greatest common factor of l and f.", "a": "2", "t": "int"}, {"q": "Let u(x) = 2*x**2 + 16*x - 9. Let o be u(-12). Let k = -55 + o. What is the highest common divisor of k and 224?", "a": "32", "t": "int"}, {"q": "Let n be (-1 + 1)*(-12 - -11). Let p be (0/(n + 2))/3. Suppose g - 2 = -3*q + 28, -2*g = p. What is the highest common factor of 40 and q?", "a": "10", "t": "int"}, {"q": "Let m be 7/((-14)/4) - 2. Let p(j) = 10 - j. Let q be p(0). Let c be (-3012)/(-30) + m/q. Calculate the greatest common divisor of c and 20.", "a": "20", "t": "int"}, {"q": "Suppose 4091*l - 3*f = 4092*l - 11, -2*f = l - 8. What is the highest common divisor of l and 3314?", "a": "2", "t": "int"}, {"q": "Suppose 4*k - 4*c - 17 = -1, -2*k = 2*c - 4. Let d be (-3)/(-2)*18/k. Calculate the greatest common divisor of 45 and d.", "a": "9", "t": "int"}, {"q": "Suppose 0 = 2*q - 5*q + 3*f + 93, 0 = 5*q - f - 135. Let p be -102 - 2/(8/(-12)). Let l = 203 + p. What is the greatest common divisor of l and q?", "a": "26", "t": "int"}, {"q": "Let l(d) = -d**3 - 6*d**2 - 3*d + 2. Let a be l(-5). Let r(s) = 4*s + 1. Let x(h) = -5*h. Let y(n) = -4*r(n) - 3*x(n). What is the units digit of y(a)?", "a": "4", "t": "int"}, {"q": "Suppose 2*p = -5*j + 3332, j = -2*p + 3*p - 1652. What is the tens digit of p?", "a": "5", "t": "int"}, {"q": "Let l be (0 + -1)*-13 + 0 + -3. Suppose -2*i = -2*f + 14, 4*f - 5*i + 0 - 31 = 0. Suppose -t = 3*m, -f*m + 2*t = -0*m - l. What is the units digit of m?", "a": "1", "t": "int"}, {"q": "Suppose -5*o - 3*n + 1178 = 0, 6*n = -4*o + 10*n + 936. What is the tens digit of o?", "a": "3", "t": "int"}, {"q": "Let d(r) = -r**3 + 3*r**2 + 5*r. Let f be d(4). Let j = 6 - f. What is the units digit of j?", "a": "2", "t": "int"}, {"q": "Suppose 4*k - 12 = -1984. Let n = k - -824. What is the units digit of n?", "a": "1", "t": "int"}, {"q": "What is the units digit of (2/4)/(3/234)?", "a": "9", "t": "int"}, {"q": "Let n(p) = 4*p**2 + 0*p**2 + 4 - 8 - 5*p**2 + 10*p. What is the units digit of n(6)?", "a": "0", "t": "int"}, {"q": "Let q(s) = 3*s - 4. Let g be q(8). Suppose 3*y - y = -g. Let d(w) = -w**2 - 9*w + 13. What is the units digit of d(y)?", "a": "3", "t": "int"}, {"q": "What is the tens digit of (-77 + 3/3)/(-2)?", "a": "3", "t": "int"}, {"q": "What is the closest to 4 in -1/3, -1, -14?", "a": "-1/3", "t": "float"}, {"q": "Which is the closest to -9?  (a) -1  (b) -1/9  (c) -2/3  (d) -3", "a": "d", "t": "string"}, {"q": "What is the nearest to 0.1 in -2.3, -1/12, -1/4, -0.1?", "a": "-1/12", "t": "float"}, {"q": "What is the nearest to -205 in -1/2, 3/2, 2/21, 1?", "a": "-1/2", "t": "float"}, {"q": "Which is the nearest to 1/2?  (a) 0.4  (b) -0.5  (c) 328", "a": "a", "t": "string"}, {"q": "What is the nearest to -1 in 0.13, -3/5, -0.1, -20?", "a": "-3/5", "t": "float"}, {"q": "Which is the nearest to -21?  (a) -0.5  (b) -0.1  (c) -17  (d) 5/3", "a": "c", "t": "string"}, {"q": "What is the closest to -2/9 in -2, -2/7, -3?", "a": "-2/7", "t": "float"}, {"q": "What is the closest to 0.1 in -6, 0.3, 5, -3/2?", "a": "0.3", "t": "float"}, {"q": "Which is the closest to 1682?  (a) 7  (b) 0.0594  (c) -0.15", "a": "a", "t": "string"}, {"q": "Let l be (15/(450/4))/((-5)/(-50)). Factor -2/3*m**4 - 2/3*m**5 - 2/3*m + l*m**2 - 2/3 + 4/3*m**3.", "a": "-2*(m - 1)**2*(m + 1)**3/3", "t": "string"}, {"q": "Let f(o) be the first derivative of -o**7/420 + o**6/30 - 3*o**5/20 - 29*o**3/3 - o**2 - 62. Let k(x) be the third derivative of f(x). Factor k(w).", "a": "-2*w*(w - 3)**2", "t": "string"}, {"q": "Let x(m) = -2*m. Let w be x(-2). Suppose 4*i - 3 = 3*i. Find k, given that 4*k**3 - 3*k**3 + i*k**4 - 2*k**w = 0.", "a": "-1, 0", "t": "tuple"}, {"q": "Let l be 320/336 - (-2)/6. Let m(j) be the first derivative of 3/2*j**2 + l*j**3 - 3 + 15/28*j**4 + 3/35*j**5 + 6/7*j. Factor m(x).", "a": "3*(x + 1)**3*(x + 2)/7", "t": "string"}, {"q": "Let c(v) be the second derivative of v**6/120 - 3*v**5/40 + v**4/4 + 11*v**3/6 + 3*v. Let i(u) be the second derivative of c(u). Find a such that i(a) = 0.", "a": "1, 2", "t": "tuple"}, {"q": "Let z(s) be the first derivative of 5*s**4/2 + 22*s**3 - 54*s**2 + 32*s + 2026. Suppose z(c) = 0. Calculate c.", "a": "-8, 2/5, 1", "t": "tuple"}, {"q": "Let g(z) be the first derivative of -3*z**5/5 - 15*z**4 - 150*z**3 - 750*z**2 - 1875*z - 2. Suppose g(a) = 0. Calculate a.", "a": "-5", "t": "int"}, {"q": "Let r(i) be the second derivative of 0 - 2/3*i**3 - 2/3*i**4 + 12*i - 1/5*i**5 + 0*i**2. Determine n so that r(n) = 0.", "a": "-1, 0", "t": "tuple"}, {"q": "Let u(r) = -294*r - 6170. Let i be u(-21). Factor 4*a**i + 0 + 16/5*a**2 - 4/5*a**5 - 32/5*a**3 + 0*a.", "a": "-4*a**2*(a - 2)**2*(a - 1)/5", "t": "string"}, {"q": "Solve 5*j**4 + 41*j + 2*j**4 - 7*j**2 - 13*j**5 - 43*j + 17*j**3 - 2*j**5 = 0.", "a": "-1, -1/5, 0, 2/3, 1", "t": "tuple"}, {"q": "Let j = -1065402/868373 + 1110/887. What is the common denominator of -41/445 and j?", "a": "4895", "t": "int"}, {"q": "What is the common denominator of -151/12 and ((-9)/(-192))/(6/4)?", "a": "96", "t": "int"}, {"q": "Let o be (-6)/15*25*-1. Suppose 4*m - 10 = -m, 3*m = 2*g - 70. What is the lowest common multiple of 4/20 + g/o and 10?", "a": "20", "t": "int"}, {"q": "Let a = -85853 + 85865. Let p(q) = -3*q**3 + q**2 + 2. What is the least common multiple of p(-2) and a?", "a": "60", "t": "int"}, {"q": "Suppose -o + z = 15, -4*o + 5*z - 62 = -0*z. What is the lowest common multiple of 112 and 1/(((-13)/8)/o)?", "a": "112", "t": "int"}, {"q": "Suppose 210 = 4*c - 5*a, 2*c - 13*a + 12*a - 108 = 0. Calculate the least common multiple of c and 14.", "a": "770", "t": "int"}, {"q": "Suppose 3*u + 4*o - 264 = 0, -4*u + 0*u + 3*o = -377. Calculate the least common multiple of u and 14.", "a": "644", "t": "int"}, {"q": "Suppose -319 - 661 = -5*m. Suppose 3*x + 0*t = 5*t + m, t + 312 = 5*x. What is the lowest common multiple of x and 4?", "a": "124", "t": "int"}, {"q": "Suppose 0 = 4*h - 5*x - 251, -27*x = -h - 24*x + 68. Let f = 129 - h. Calculate the lowest common multiple of 217 and f.", "a": "2170", "t": "int"}, {"q": "Let s = -87/1402 - 1056059/5608. Let b = s - -181. Calculate the common denominator of 34 and b.", "a": "8", "t": "int"}, {"q": "Factor -y**4/7 + 13*y**2/7 - 12*y/7.", "a": "-y*(y - 3)*(y - 1)*(y + 4)/7", "t": "string"}, {"q": "Suppose -3*k**4/5 - 273*k**3/5 - 2697*k**2/5 - 4587*k/5 - 432 = 0. Calculate k.", "a": "-80, -9, -1", "t": "tuple"}, {"q": "What is p in -3*p**4 - 201*p**3 - 4425*p**2 - 31875*p = 0?", "a": "-25, -17, 0", "t": "tuple"}, {"q": "Solve -3*t**2/7 + 2391621*t/7 - 4783230/7 = 0 for t.", "a": "2, 797205", "t": "tuple"}, {"q": "Factor -5*d**3 + 60*d**2 - 205*d + 150.", "a": "-5*(d - 6)*(d - 5)*(d - 1)", "t": "string"}, {"q": "Solve -2*m**5/3 - 12*m**4 - 190*m**3/3 - 292*m**2/3 + 40*m + 400/3 = 0 for m.", "a": "-10, -5, -2, 1", "t": "tuple"}, {"q": "Factor 2*t**3 - 38*t**2 - 240*t.", "a": "2*t*(t - 24)*(t + 5)", "t": "string"}, {"q": "Solve -2*f**2/5 - 397968*f/5 - 19797316128/5 = 0 for f.", "a": "-99492", "t": "int"}, {"q": "Suppose -j**4/3 - 78497*j**3/3 + 104667*j**2 - 78501*j = 0. Calculate j.", "a": "-78501, 0, 1, 3", "t": "tuple"}, {"q": "Solve 2*t**5 - 62988*t**4 - 63016*t**3 + 818868*t**2 + 63014*t - 755880 = 0 for t.", "a": "-4, -1, 1, 3, 31495", "t": "tuple"}, {"q": "Is 3491 prime?", "a": "True", "t": "bool"}, {"q": "Is 18637 prime?", "a": "True", "t": "bool"}, {"q": "Is 2119229 a prime number?", "a": "False", "t": "bool"}, {"q": "Is 132299 a composite number?", "a": "False", "t": "bool"}, {"q": "Is 111860191 composite?", "a": "True", "t": "bool"}, {"q": "Is 1486833 a composite number?", "a": "True", "t": "bool"}, {"q": "Is 561899 a composite number?", "a": "True", "t": "bool"}, {"q": "Is 1088893018 prime?", "a": "False", "t": "bool"}, {"q": "Is 463769 a composite number?", "a": "True", "t": "bool"}, {"q": "Is 522303 a prime number?", "a": "False", "t": "bool"}, {"q": "What is the lowest common multiple of 3824 and 2868?", "a": "11472", "t": "int"}, {"q": "What is the lowest common multiple of 814 and 91612?", "a": "1007732", "t": "int"}, {"q": "What is the smallest common multiple of 1518 and 2277?", "a": "4554", "t": "int"}, {"q": "Find the common denominator of 71/1062012 and 17/12.", "a": "1062012", "t": "int"}, {"q": "Calculate the common denominator of -139/1278 and -43/284.", "a": "2556", "t": "int"}, {"q": "Find the common denominator of 29/119574 and -50/4842747.", "a": "9685494", "t": "int"}, {"q": "Calculate the common denominator of 19/63 and -173/504.", "a": "504", "t": "int"}, {"q": "Calculate the smallest common multiple of 912 and 69248.", "a": "3947136", "t": "int"}, {"q": "What is the least common multiple of 18466 and 10?", "a": "92330", "t": "int"}, {"q": "Calculate the common denominator of -13/1051363 and -52/179501.", "a": "7359541", "t": "int"}, {"q": "Let r = 263438.469 + 534.531. Let t = 263706.159 - r. Let q = t - -267. What is q rounded to two dps?", "a": "0.16", "t": "float"}, {"q": "Let h = -10.55 + 516.55. Let i = -499.22 + h. Round i to 1 dp.", "a": "6.8", "t": "float"}, {"q": "Let l = 16 - 4. Suppose l*w = 10*w. Suppose -5*u - 714145 + 214145 = w. What is u rounded to the nearest 100000?", "a": "-100000", "t": "int"}, {"q": "Suppose -162 = -8*c + 30. Let j be 5/(-1)*c/(-40). Suppose 3*r - 12 = 6*r, -j*s - r - 6484 = 0. Round s to the nearest one hundred.", "a": "-2200", "t": "int"}, {"q": "Let d = -44 - -43.936. What is d rounded to two decimal places?", "a": "-0.06", "t": "float"}, {"q": "Let q = 743 - 52. Let t = -707.15 + q. Let o = t + 17. Round o to one decimal place.", "a": "0.9", "t": "float"}, {"q": "Let w be 15/10*12/9. Suppose 0 = 3*d - w*d - 3. Suppose r = 2*r - d*u - 187003, -r + 186996 = 4*u. Round r to the nearest ten thousand.", "a": "190000", "t": "int"}, {"q": "Let k(d) = 521*d + 3. Let a be k(2). Let c = -735 + a. Suppose 0 = x - 5*z + c, -3*z = x - 2*z + 334. What is x rounded to the nearest one hundred?", "a": "-300", "t": "int"}, {"q": "Let v = 1.4 - 2.6. Let y = -2.4 + v. Round y to the nearest integer.", "a": "-4", "t": "int"}, {"q": "Let m = -1.57 - -8.67. Round m to zero decimal places.", "a": "7", "t": "int"}, {"q": "Which is greater: 217377 or 217372?", "a": "217377", "t": "int"}, {"q": "Which is bigger: -152188 or -152189?", "a": "-152188", "t": "int"}, {"q": "Which is smaller: -1 or 33/157544?", "a": "-1", "t": "int"}, {"q": "Which is bigger: 1 or -97?", "a": "1", "t": "int"}, {"q": "Which is smaller: -27134 or -33893?", "a": "-33893", "t": "int"}, {"q": "Which is smaller: 1/2 or 47/3?", "a": "1/2", "t": "float"}, {"q": "Which is smaller: 23/314 or 0?", "a": "0", "t": "int"}, {"q": "Does 1 = 88/125?", "a": "False", "t": "bool"}, {"q": "Is -903 greater than -902?", "a": "False", "t": "bool"}, {"q": "Do 51 and 54 have different values?", "a": "True", "t": "bool"}, {"q": "What is the eighth root of 200310018 to the nearest integer?", "a": "11", "t": "int"}, {"q": "What is 256898883 to the power of 1/4, to the nearest integer?", "a": "127", "t": "int"}, {"q": "What is the fourth root of 2299991 to the nearest integer?", "a": "39", "t": "int"}, {"q": "What is 61159311 to the power of 1/6, to the nearest integer?", "a": "20", "t": "int"}, {"q": "What is the ninth root of 86308559 to the nearest integer?", "a": "8", "t": "int"}, {"q": "What is the cube root of 850 to the nearest integer?", "a": "9", "t": "int"}, {"q": "What is 1404464199 to the power of 1/2, to the nearest integer?", "a": "37476", "t": "int"}, {"q": "What is the square root of 105252115 to the nearest integer?", "a": "10259", "t": "int"}, {"q": "What is the square root of 48024271 to the nearest integer?", "a": "6930", "t": "int"}, {"q": "What is 153058351 to the power of 1/3, to the nearest integer?", "a": "535", "t": "int"}, {"q": "Rearrange 28*g - 88*g + 5*g + 12*g to the form j + h*g and give j.", "a": "0", "t": "int"}, {"q": "Express 12*o + 5*o - 6*o as x*o + w and give w.", "a": "0", "t": "int"}, {"q": "Express 2*w**4 - 686 + 7*w**2 - w + 686 - w**3 in the form b*w**3 + a*w**4 + x*w + y + l*w**2 and give a.", "a": "2", "t": "int"}, {"q": "Rearrange 27*d**2 - 5 - 2 + 7 to k*d**2 + m + c*d and give k.", "a": "27", "t": "int"}, {"q": "Express (-2*u + 3*u + 5*u)*(25 + 44 - 34)*(1 - 1 + 2*u) as g*u + q*u**2 + b and give q.", "a": "420", "t": "int"}, {"q": "Rearrange 66*h - 132*h - 183*h to the form f + a*h and give a.", "a": "-249", "t": "int"}, {"q": "Rearrange -73*b**3 - 13*b**4 + 11*b**4 + 2*b - 9879 + b**2 + 9880 to the form g*b + w + r*b**4 + a*b**3 + t*b**2 and give w.", "a": "1", "t": "int"}, {"q": "Rearrange 8 - 4 - 2*k**3 + 18 to c + r*k**3 + t*k + i*k**2 and give r.", "a": "-2", "t": "int"}, {"q": "Express 599785*u - 1173*u**2 - 299893*u + 4 - 299892*u in the form k + b*u + y*u**2 and give k.", "a": "4", "t": "int"}, {"q": "Rearrange 2 + 20*n**2 - 98*n**3 - 1423*n + 97*n**3 + 1435*n to s*n**2 + v + m*n**3 + t*n and give m.", "a": "-1", "t": "int"}, {"q": "What is the hundred thousands digit of 24917548?", "a": "9", "t": "int"}, {"q": "What is the hundred thousands digit of 128999?", "a": "1", "t": "int"}, {"q": "What is the millions digit of 1985541?", "a": "1", "t": "int"}, {"q": "What is the millions digit of 225497583?", "a": "5", "t": "int"}, {"q": "What is the ten thousands digit of 61554718?", "a": "5", "t": "int"}, {"q": "What is the hundreds digit of 16344024?", "a": "0", "t": "int"}, {"q": "What is the units digit of 14030851?", "a": "1", "t": "int"}, {"q": "What is the thousands digit of 1727?", "a": "1", "t": "int"}, {"q": "What is the hundreds digit of 3606?", "a": "6", "t": "int"}, {"q": "What is the tens digit of 848936921?", "a": "2", "t": "int"}, {"q": "36/90*-5*(-8)/(-1)", "a": "-16", "t": "int"}, {"q": "What is the value of 6*(-20)/(-3510)*13?", "a": "4/9", "t": "float"}, {"q": "What is the value of ((-6)/(-81))/((-7140)/(-6940080))?", "a": "72", "t": "int"}, {"q": "What is the value of -1*(3 + (-65)/20)*4?", "a": "1", "t": "int"}, {"q": "(8880/(-37))/60 - 47", "a": "-51", "t": "int"}, {"q": "What is 575/(-55) - 3 - (-96)/(-176)?", "a": "-14", "t": "int"}, {"q": "19*-19*(-28)/(-532)", "a": "-19", "t": "int"}, {"q": "(-360)/(-144)*-2*18/(-10)", "a": "9", "t": "int"}, {"q": "What is (7*-3 - 108/(-5))*10/(-138)?", "a": "-1/23", "t": "float"}, {"q": "(7*(-6)/(2 + 4))/((-3)/(-3))", "a": "-7", "t": "int"}, {"q": "What is the value of (-2 + 1 - -5) + (-60 - -58)?", "a": "2", "t": "int"}, {"q": "What is the value of 3 + -7 + 2 - -15?", "a": "13", "t": "int"}, {"q": "Evaluate -18 - -27 - (14 + 1).", "a": "-6", "t": "int"}, {"q": "Evaluate 1 + -51 + -14 + (8 - -14) + -17.", "a": "-59", "t": "int"}, {"q": "What is 0 + -79 - (-1733 + 1705)?", "a": "-51", "t": "int"}, {"q": "What is the value of -5 - (3 + (1 - 5))?", "a": "-4", "t": "int"}, {"q": "2 + -7 + -3 + 5 - (-1109 + 1121)", "a": "-15", "t": "int"}, {"q": "Evaluate -18 + (35 - (5 + -13)) - 3.", "a": "22", "t": "int"}, {"q": "Calculate 9 + (-41 + 44 + (3 - -7) - (-20 + 17)).", "a": "25", "t": "int"}, {"q": "0 + 7 - (-1 + (12 - 8))", "a": "4", "t": "int"}, {"q": "What is next in 1088, 976, 782, 500, 124, -352, -934, -1628?", "a": "-2440", "t": "int"}, {"q": "What comes next: -46689488, -46689441, -46689396, -46689353, -46689312, -46689273, -46689236?", "a": "-46689201", "t": "int"}, {"q": "What comes next: -107, -116, -135, -170, -227, -312, -431?", "a": "-590", "t": "int"}, {"q": "What is the next term in 90, 391, 900, 1623, 2566, 3735?", "a": "5136", "t": "int"}, {"q": "What is the next term in 18, 25, 20, -3, -50, -127?", "a": "-240", "t": "int"}, {"q": "What is next in 37, 148, 311, 514, 745, 992, 1243, 1486?", "a": "1709", "t": "int"}, {"q": "What is the next term in 3679897, 7359832, 11039767, 14719702, 18399637, 22079572?", "a": "25759507", "t": "int"}, {"q": "What is the next term in 2126, 7088, 12052, 17018?", "a": "21986", "t": "int"}, {"q": "What is next in -2060, -1941, -1738, -1445, -1056, -565?", "a": "34", "t": "int"}, {"q": "What comes next: -39, 532, 1925, 4488, 8569?", "a": "14516", "t": "int"}, {"q": "-22 (base 13) to base 11", "a": "-26", "t": "int"}, {"q": "What is 20002110 (base 3) in base 6?", "a": "32320", "t": "int"}, {"q": "Convert 3441102 (base 5) to base 12.", "a": "2ba8b", "t": "string"}, {"q": "10378 (base 10) to base 6", "a": "120014", "t": "int"}, {"q": "What is 33333322 (base 4) in base 10?", "a": "65530", "t": "int"}, {"q": "What is -1201210012 (base 3) in base 13?", "a": "-126a7", "t": "string"}, {"q": "What is 1 (base 2) in base 8?", "a": "1", "t": "int"}, {"q": "-610310 (base 8) to base 13", "a": "-705a2", "t": "string"}, {"q": "Convert -4321455 (base 6) to base 7.", "a": "-1544546", "t": "int"}, {"q": "Convert 727098 (base 12) to base 7.", "a": "21155501", "t": "int"}, {"q": "How many centuries are there in 17.788284 months?", "a": "0.01482357", "t": "float"}, {"q": "What is fifty-one fifths of a gram in milligrams?", "a": "10200", "t": "int"}, {"q": "Convert 939.4911ml to litres.", "a": "0.9394911", "t": "float"}, {"q": "Convert 725900.427ns to weeks.", "a": "0.0000000012002321875", "t": "float"}, {"q": "How many weeks are there in 9.9180963s?", "a": "0.00001639896875", "t": "float"}, {"q": "What is eleven quarters of a tonne in kilograms?", "a": "2750", "t": "int"}, {"q": "What is 1/4 of a millisecond in microseconds?", "a": "250", "t": "int"}, {"q": "Convert 34.06329 microseconds to nanoseconds.", "a": "34063.29", "t": "float"}, {"q": "What is 352292.3mm in micrometers?", "a": "352292300", "t": "int"}, {"q": "How many milligrams are there in 630277.6 nanograms?", "a": "0.6302776", "t": "float"}, {"q": "In base 10, what is 4344791 - -1?", "a": "4344792", "t": "int"}, {"q": "In base 11, what is 124 - -8588?", "a": "8701", "t": "int"}, {"q": "In base 5, what is 300 + -10?", "a": "240", "t": "int"}, {"q": "In base 16, what is 168b9 - -15e3?", "a": "17e9c", "t": "string"}, {"q": "In base 3, what is -20212210 - 101100?", "a": "-21021010", "t": "int"}, {"q": "In base 7, what is -3 - -2056?", "a": "2053", "t": "int"}, {"q": "In base 7, what is -2 - -261?", "a": "256", "t": "int"}, {"q": "In base 4, what is 212 + 122?", "a": "1000", "t": "int"}, {"q": "In base 13, what is 863 - 15c?", "a": "704", "t": "int"}, {"q": "In base 14, what is -3b4 + 5?", "a": "-3ad", "t": "string"}, {"q": "Suppose -9*s + 36 = -8*s. Is 18 a factor of s?", "a": "True", "t": "bool"}, {"q": "Let x(j) be the first derivative of -89*j**2/2 - 3*j - 14. Is x(-2) a multiple of 16?", "a": "False", "t": "bool"}, {"q": "Let n be ((-2)/(-6))/((-4)/(-48)). Suppose -b - n*b = -5*a + 10, 2*a - 16 = 5*b. Does 13 divide 0/(-4 - a) - 464/(-4)?", "a": "False", "t": "bool"}, {"q": "Suppose 12*m - 16*m - 16 = 0, -m - 180 = -k. Does 33 divide k?", "a": "False", "t": "bool"}, {"q": "Let r(n) be the first derivative of n**4/4 + n**3 - n**2/2 - 2*n - 1. Let j be r(-3). Does 14 divide 29/(j/(-2 - -3))?", "a": "False", "t": "bool"}, {"q": "Let l = -20 + 3. Let a = 6 - -53. Let k = l + a. Is 12 a factor of k?", "a": "False", "t": "bool"}, {"q": "Let h(z) = -z**2 + 9*z + 19. Let b be h(10). Does 5 divide 9 + -7 + 2*b?", "a": "True", "t": "bool"}, {"q": "Let o be (-1 + -4)*(2 + 6/(-5)). Does 16 divide (18/12)/(o/(-1408))?", "a": "True", "t": "bool"}, {"q": "Suppose 0 = 4*g - 156 + 36. Is 5 a factor of g?", "a": "True", "t": "bool"}, {"q": "Suppose c + 2*c - 534 = 0. Is 42 a factor of c?", "a": "False", "t": "bool"}, {"q": "Let z(m) = -m**3 - 41*m**2 - 54*m - 258. Calculate z(-40).", "a": "302", "t": "int"}, {"q": "Let i(k) = -7*k - 222. Give i(-32).", "a": "2", "t": "int"}, {"q": "Let a(j) = -88*j - 9599. Determine a(-107).", "a": "-183", "t": "int"}, {"q": "Let k(b) = -5059*b - 50551. Determine k(-10).", "a": "39", "t": "int"}, {"q": "Let i(j) = 2*j**2 - 42*j - 38. What is i(21)?", "a": "-38", "t": "int"}, {"q": "Let h(a) = 7*a**3 - a**2 + 28*a - 100. Determine h(3).", "a": "164", "t": "int"}, {"q": "Let r(x) = -x**3 - 5*x**2 - 19*x - 51. Give r(-4).", "a": "9", "t": "int"}, {"q": "Let l(z) = 192 - 245*z. Calculate l(0).", "a": "192", "t": "int"}, {"q": "Let n(x) = -8*x - 3. Calculate n(3).", "a": "-27", "t": "int"}, {"q": "Let d(w) = 15*w + 102. Give d(-11).", "a": "-63", "t": "int"}, {"q": "-10.8 * 6", "a": "-64.8", "t": "float"}, {"q": "-0.49*2.2", "a": "-1.078", "t": "float"}, {"q": "0.213716 * 1079", "a": "230.599564", "t": "float"}, {"q": "Multiply -0.5 and -2013642.", "a": "1006821", "t": "int"}, {"q": "Work out -2 * 433.", "a": "-866", "t": "int"}, {"q": "Multiply 254 and 1.328.", "a": "337.312", "t": "float"}, {"q": "0.02448861*2", "a": "0.04897722", "t": "float"}, {"q": "0.1 times -31.4", "a": "-3.14", "t": "float"}, {"q": "What is the product of -56 and 44485.2?", "a": "-2491171.2", "t": "float"}, {"q": "Calculate -11.56*4.488.", "a": "-51.88128", "t": "float"}, {"q": "Two letters picked without replacement from tlnplzw. Give prob of sequence nz.", "a": "1/42", "t": "float"}, {"q": "Two letters picked without replacement from gogyongyyyiyo. Give prob of sequence go.", "a": "3/52", "t": "float"}, {"q": "Four letters picked without replacement from dqqqqqdqqqqqqqqqqqq. Give prob of sequence dqqq.", "a": "5/57", "t": "float"}, {"q": "Two letters picked without replacement from cyyycygyyyyccy. Give prob of sequence gc.", "a": "2/91", "t": "float"}, {"q": "What is prob of sequence gjc when three letters picked without replacement from cjccguuujujgjmjcjj?", "a": "7/612", "t": "float"}, {"q": "Calculate prob of sequence ay when two letters picked without replacement from aayyyyyyyyyyay.", "a": "33/182", "t": "float"}, {"q": "Four letters picked without replacement from {t: 2, b: 1, y: 1, r: 1}. Give prob of sequence ybtr.", "a": "1/60", "t": "float"}, {"q": "Calculate prob of sequence ravb when four letters picked without replacement from arvrebr.", "a": "1/280", "t": "float"}, {"q": "Calculate prob of sequence iiee when four letters picked without replacement from eeiihieihehiiieieei.", "a": "21/646", "t": "float"}, {"q": "What is prob of sequence fif when three letters picked without replacement from ififiiffffiifffi?", "a": "3/20", "t": "float"}, {"q": "Let a be (1 - 4)*(-24)/18. Find the second derivative of -2*d - 18*d**3 - a*d + 11*d**3 wrt d.", "a": "-42*d", "t": "string"}, {"q": "Suppose 23*y = 24*y - 31. What is the second derivative of y*r - 26*r - 9*r**3 - 19*r wrt r?", "a": "-54*r", "t": "string"}, {"q": "Let c(w) be the second derivative of w**7/120 - w**5/20 - 5*w**3/6 - 11*w. Let b(v) be the second derivative of c(v). Find the second derivative of b(r) wrt r.", "a": "42*r", "t": "string"}, {"q": "Suppose -5*k + 25 = 0, 8*k - 3*k - 620 = -5*d. What is the third derivative of 55*x**3 + 59*x**3 - d*x**3 + 11*x**2 wrt x?", "a": "-30", "t": "int"}, {"q": "Find the first derivative of -22*b**4 - 30 + 55 - 26 wrt b.", "a": "-88*b**3", "t": "string"}, {"q": "Find the second derivative of -11*n**2 + 5 - 2 + 11*n - 4 wrt n.", "a": "-22", "t": "int"}, {"q": "Let l(f) be the first derivative of -1922*f**3/3 - 2325*f - 748. What is the derivative of l(m) wrt m?", "a": "-3844*m", "t": "string"}, {"q": "Find the third derivative of -107*o**2 - 2*o + 19*o**4 + 67*o**2 + 82*o**4 + 3*o wrt o.", "a": "2424*o", "t": "string"}, {"q": "Let l(v) be the second derivative of 8*v**3 + 1/2*v**2 + 166*v + 71/12*v**4 + 0. Find the second derivative of l(h) wrt h.", "a": "142", "t": "int"}, {"q": "Find the second derivative of 597*b**4 + 125*b**4 + 9*b**4 - 341*b - 868*b - 14*b wrt b.", "a": "8772*b**2", "t": "string"}, {"q": "Let x(g) = 11 - 13*g**2. Let l(t) be the second derivative of -7*t**4/12 + 3*t**2 + t. Let h = 4 + 2. Let k be (-2 + 1)/((-5)/(-55)). Determine h*x(u) + k*l(u).", "a": "-u**2", "t": "string"}, {"q": "Let k(l) = -2*l**3 - 6*l**2 + 8. Let t(q) = -q**3 - 2*q**2 + 3. What is -3*k(i) + 8*t(i)?", "a": "-2*i**3 + 2*i**2", "t": "string"}, {"q": "Let p = -50 - -57. Let k(q) = -q**2 - 2*q - 1. Let c(u) = -2*u**2 - 5*u - 2. Calculate p*k(d) - 3*c(d).", "a": "-d**2 + d - 1", "t": "string"}, {"q": "Let a(w) = -2*w**2 - 3*w. Let d(p) be the third derivative of p**5/20 + 5*p**4/24 - p**2. Let c be (0 - 228)/(-19) - 2. Calculate c*a(k) + 6*d(k).", "a": "-2*k**2", "t": "string"}, {"q": "Let v(w) = -4*w - 2. Let y(x) = -9*x - 5. Let r(l) = 2*l**2 - 3*l - 3. Suppose a + a - 8 = 0. Let t = 7 - a. Let c be r(t). Calculate c*y(i) - 14*v(i).", "a": "2*i - 2", "t": "string"}, {"q": "Let x(y) = -4*y**3 + 2*y**2 - 2*y. Suppose 5 - 11 = 3*w. Let n(p) = 3*p**3 - 3*p**2 + 3*p. Give w*n(l) - 3*x(l).", "a": "6*l**3", "t": "string"}, {"q": "Let i(l) = 270*l**2 - 4*l. Let j(w) = 2*w. Determine 3*i(t) + 6*j(t).", "a": "810*t**2", "t": "string"}, {"q": "Let f(j) = 6*j**3. Let g(a) = 2*a**3 - a**3 + a**3 + 2*a**3. Suppose 0 = 4*k + 5*u - 42, -k + 28 = 3*k - 2*u. Determine k*g(b) - 5*f(b).", "a": "2*b**3", "t": "string"}, {"q": "Let m(p) = 4*p**2 + 9*p - 5. Let o(c) = -c**2 - 5*c - 1. Let k(z) = 8*z**2 + 23*z - 6. Let t(v) = -k(v) - 2*o(v). Determine -8*m(w) - 5*t(w).", "a": "-2*w**2 - 7*w", "t": "string"}, {"q": "Let d(w) = -3. Let m(j) = 1 - j. Let x be m(-4). Let i(q) = q - 6. Suppose -3570 + 3552 = 9*c. Give c*i(p) + x*d(p).", "a": "-2*p - 3", "t": "string"}, {"q": "Simplify (-2*-2*sqrt(800))/(4*sqrt(80)/(sqrt(8) - sqrt(128))).", "a": "-12*sqrt(5)", "t": "string"}, {"q": "Simplify (3*3*(sqrt(77) + -1*sqrt(77)))/(sqrt(1100)*-2 - -3*sqrt(11)*-1).", "a": "0", "t": "int"}, {"q": "Simplify (-1*(sqrt(119) - sqrt(119)*-3))/sqrt(4032).", "a": "-sqrt(17)/6", "t": "string"}, {"q": "Simplify (-5*(-3 + sqrt(891)) + 1 + (sqrt(891) - (4 + sqrt(891))))**2*-1*-1.", "a": "22419 - 1080*sqrt(11)", "t": "string"}, {"q": "Simplify ((sqrt(539)*3)**2 - sqrt(77)/(sqrt(7)*1)) + 3.", "a": "4854 - sqrt(11)", "t": "string"}, {"q": "Simplify 1*(sqrt(175)*1)**2 - (1 + sqrt(7)*-1)*5.", "a": "5*sqrt(7) + 170", "t": "string"}, {"q": "Simplify sqrt(45)/(sqrt(225) - sqrt(225)*-2).", "a": "sqrt(5)/15", "t": "string"}, {"q": "Simplify (sqrt(19) + sqrt(2736) + 0 + -4)**2 + 0.", "a": "3227 - 104*sqrt(19)", "t": "string"}, {"q": "Simplify -2*((-3 + sqrt(432)*4)**2 + sqrt(432) - -1*-3*sqrt(432)).", "a": "-13842 + 624*sqrt(3)", "t": "string"}, {"q": "Simplify (-2 + 3 + 1*(-1 + sqrt(700) + -1) + sqrt(700) + 2 + 0 + 4*3*sqrt(700))**2.", "a": "280*sqrt(7) + 137201", "t": "string"}, {"q": "Simplify ((m**(-2/15)/m*m)/m**(-3/11)*(m**(-19))**(-33/7))**(-9/4) assuming m is positive.", "a": "m**(-77712/385)", "t": "string"}, {"q": "Simplify (c**(-1/2)*c*c**(1/4))/(c*c*c**(-6/7)*c*c**(2/27)) assuming c is positive.", "a": "c**(-1109/756)", "t": "string"}, {"q": "Simplify ((c/(c*c**(-1/3)/c)*c**(2/7)*c)/(c/c**(2/7))**38)/((c*c/((c*c**(-3/8)*c)/c))/(c*c**2))**(2/119) assuming c is positive.", "a": "c**(-34981/1428)", "t": "string"}, {"q": "Simplify (b**(-1/5)*b)/(b/(b/(b/((b**5*b)/b))*b))*(b*(b/(b/((b*b**(-2/5))/b*b))*b)/b)/b**3 assuming b is positive.", "a": "b**(22/5)", "t": "string"}, {"q": "Simplify (l**0)**(-5/18)*(l*l*(l**(-1)/l)/l)**(-11/7) assuming l is positive.", "a": "l**(11/7)", "t": "string"}, {"q": "Simplify ((l*l**(-1))**(-3/11)*l**5/((l*l*l/(l*l*l**(2/23)))/l))/(l**(-3)/l*l*l**(-2)*l*l)**(-30/13) assuming l is positive.", "a": "l**(-549/299)", "t": "string"}, {"q": "Simplify ((((o**0)**(1/20))**(-6))**0)**(-32) assuming o is positive.", "a": "1", "t": "int"}, {"q": "Simplify ((q*q*(q**(-3/2)*q)/q)/(q/(q/(q*q**7*q))))**(-39) assuming q is positive.", "a": "q**(663/2)", "t": "string"}, {"q": "Simplify (r**5/((r*r**(6/5)*r)/r))/(r*r/r**(1/6)*r**(-10)/r*r) assuming r is positive.", "a": "r**(329/30)", "t": "string"}, {"q": "Simplify d**21/d**(-1/9)*d**(1/9)*d**(-7) assuming d is positive.", "a": "d**(128/9)", "t": "string"}, {"q": "Let n(t) = t**2 + 11*t - 3. Let w be n(-12). Is 9/6*78/w prime?", "a": "True", "t": "bool"}, {"q": "Let w = -56 + 447. Is w composite?", "a": "True", "t": "bool"}, {"q": "Suppose 22 = -6*p - 5*p. Let m(s) = -220*s**3 - s**2 - 5*s - 7. Is m(p) a composite number?", "a": "False", "t": "bool"}, {"q": "Suppose 55983 = 22*k - 9731. Is k a prime number?", "a": "False", "t": "bool"}, {"q": "Let v = 278 - 164. Let l be (-1)/6 - (-1259035)/v. Is 4/18 - l/(-36) prime?", "a": "True", "t": "bool"}, {"q": "Let u(q) = 219*q - 2. Let y(c) = 1105 - 120887*c. Let r(i) = -1105*u(i) - 2*y(i). Is r(-1) a composite number?", "a": "True", "t": "bool"}, {"q": "Suppose 2*q = 273 + 91. Suppose 0 = 4*l - 2638 + q. Is l a prime number?", "a": "False", "t": "bool"}, {"q": "Is (-121)/(3/(-3 + 0)) a composite number?", "a": "True", "t": "bool"}, {"q": "Suppose 3*y - 3*r = -y + 1, 5*r = 3*y + 13. Suppose -3*i = -y*v - 386, -3*v - 524 = -4*i - 0*v. Suppose 5*g = 4*g + i. Is g a composite number?", "a": "True", "t": "bool"}, {"q": "Let k(i) = -i**3 + 9*i**2 + 3*i + 10. Let a(m) = 3*m - 9. Let h(d) = -d**2 - 5*d + 2. Let n be h(-4). Let v be a(n). Is k(v) composite?", "a": "False", "t": "bool"}, {"q": "What is the smallest value in -2, 7233.29, 14?", "a": "-2", "t": "int"}, {"q": "Which is the biggest value?  (a) 1/2  (b) 2  (c) 0.3  (d) -72.5  (e) 7/2", "a": "e", "t": "string"}, {"q": "Which is the fourth smallest value?  (a) 49.1  (b) -2  (c) 0.004  (d) 1  (e) -5  (f) -2/5", "a": "c", "t": "string"}, {"q": "What is the second biggest value in -10/13, 2, -34, -0.2?", "a": "-0.2", "t": "float"}, {"q": "What is the fourth biggest value in 5, 4/39, 9, -0.097?", "a": "-0.097", "t": "float"}, {"q": "Which is the third biggest value?  (a) -16  (b) -4  (c) -2  (d) 115  (e) -3/7", "a": "c", "t": "string"}, {"q": "Which is the smallest value?  (a) 0  (b) -18/53  (c) -1/4  (d) -0.3", "a": "b", "t": "string"}, {"q": "Which is the third smallest value?  (a) 1/249  (b) -6.7  (c) 0.288", "a": "c", "t": "string"}, {"q": "Which is the biggest value?  (a) 2  (b) -13  (c) 0.1", "a": "a", "t": "string"}, {"q": "Which is the smallest value?  (a) 0  (b) -101  (c) 10  (d) -1", "a": "b", "t": "string"}, {"q": "3727260 divided by -180", "a": "-20707", "t": "int"}, {"q": "What is 323 divided by -6?", "a": "-323/6", "t": "float"}, {"q": "Calculate 161386 divided by 8494.", "a": "19", "t": "int"}, {"q": "Calculate 3690 divided by -205.", "a": "-18", "t": "int"}, {"q": "What is 3739230 divided by -6?", "a": "-623205", "t": "int"}, {"q": "Divide -8 by 62471.", "a": "-8/62471", "t": "float"}, {"q": "-1033 divided by -73373", "a": "1033/73373", "t": "float"}, {"q": "-363 divided by 83", "a": "-363/83", "t": "float"}, {"q": "4 divided by -127", "a": "-4/127", "t": "float"}, {"q": "79224 divided by 8", "a": "9903", "t": "int"}, {"q": "Round 0.0034081 to four decimal places.", "a": "0.0034", "t": "float"}, {"q": "What is 0.00009698 rounded to six decimal places?", "a": "0.000097", "t": "float"}, {"q": "What is -145498.9107 rounded to the nearest one thousand?", "a": "-145000", "t": "int"}, {"q": "What is 0.150346 rounded to two dps?", "a": "0.15", "t": "float"}, {"q": "What is 2188170 rounded to the nearest one hundred thousand?", "a": "2200000", "t": "int"}, {"q": "What is 1385440.65 rounded to the nearest one hundred thousand?", "a": "1400000", "t": "int"}, {"q": "Round -663041.021 to the nearest 1000.", "a": "-663000", "t": "int"}, {"q": "Round -0.0000817892 to 6 decimal places.", "a": "-0.000082", "t": "float"}, {"q": "Round 0.000016009987 to six decimal places.", "a": "0.000016", "t": "float"}, {"q": "What is -0.0631 rounded to two dps?", "a": "-0.06", "t": "float"}, {"q": "Solve 336*p - 2745 = -243*p + 5361 for p.", "a": "14", "t": "int"}, {"q": "Solve -1000*y + 1054*y - 81 + 27 = 0 for y.", "a": "1", "t": "int"}, {"q": "Solve -40*d + 91 + 72 + 77 = 0 for d.", "a": "6", "t": "int"}, {"q": "Solve -206*c + 1111 = -166 - 989 for c.", "a": "11", "t": "int"}, {"q": "Solve -1561*j + 4016*j = -1934*j + 416955 for j.", "a": "95", "t": "int"}, {"q": "Solve 13240995 - 13248395 = -185*q for q.", "a": "40", "t": "int"}, {"q": "Solve -18*u - 278*u = -60*u - 1888 for u.", "a": "8", "t": "int"}, {"q": "Solve 4*a + 3 = -13 for a.", "a": "-4", "t": "int"}, {"q": "Solve 7*u + 572 - 628 = 0 for u.", "a": "8", "t": "int"}, {"q": "Solve 55 = -10*w + 15 for w.", "a": "-4", "t": "int"}]